AtomFlightManualZhCn/README.md
AtomFlightManualZhCn/__init__.py
AtomFlightManualZhCn/__main__.py
AtomFlightManualZhCn/file.epub
AtomFlightManualZhCn/index.html
AtomFlightManualZhCn/css/__init__.py
AtomFlightManualZhCn/css/annotations.css
AtomFlightManualZhCn/css/main.css
AtomFlightManualZhCn/css/normalize.css
AtomFlightManualZhCn/css/popup.css
AtomFlightManualZhCn/font/__init__.py
AtomFlightManualZhCn/font/fontello.eot
AtomFlightManualZhCn/font/fontello.svg
AtomFlightManualZhCn/font/fontello.ttf
AtomFlightManualZhCn/font/fontello.woff
AtomFlightManualZhCn/img/__init__.py
AtomFlightManualZhCn/img/annotator-glyph-sprite.png
AtomFlightManualZhCn/img/annotator-icon-sprite.png
AtomFlightManualZhCn/img/apple-touch-icon.png
AtomFlightManualZhCn/img/cancelfullscreen.png
AtomFlightManualZhCn/img/close.png
AtomFlightManualZhCn/img/fullscreen.png
AtomFlightManualZhCn/img/loader.gif
AtomFlightManualZhCn/img/menu-icon.png
AtomFlightManualZhCn/img/save.png
AtomFlightManualZhCn/img/saved.png
AtomFlightManualZhCn/img/settings-s.png
AtomFlightManualZhCn/img/settings.png
AtomFlightManualZhCn/img/star.png
AtomFlightManualZhCn/js/__init__.py
AtomFlightManualZhCn/js/epub.js
AtomFlightManualZhCn/js/epub.min.js
AtomFlightManualZhCn/js/epub.min.map
AtomFlightManualZhCn/js/hooks.min.js
AtomFlightManualZhCn/js/hooks.min.map
AtomFlightManualZhCn/js/reader.js
AtomFlightManualZhCn/js/reader.js.map
AtomFlightManualZhCn/js/reader.min.js
AtomFlightManualZhCn/js/reader.min.map
AtomFlightManualZhCn/js/hooks/__init__.py
AtomFlightManualZhCn/js/hooks/extensions/__init__.py
AtomFlightManualZhCn/js/hooks/extensions/highlight.js
AtomFlightManualZhCn/js/libs/__init__.py
AtomFlightManualZhCn/js/libs/jquery.min.js
AtomFlightManualZhCn/js/libs/localforage.min.js
AtomFlightManualZhCn/js/libs/screenfull.js
AtomFlightManualZhCn/js/libs/screenfull.min.js
AtomFlightManualZhCn/js/libs/zip.min.js
AtomFlightManualZhCn/js/plugins/__init__.py
AtomFlightManualZhCn/js/plugins/hypothesis.js
atom_flight_manual_zh_cn-2024.3.1.0.dist-info/METADATA
atom_flight_manual_zh_cn-2024.3.1.0.dist-info/WHEEL
atom_flight_manual_zh_cn-2024.3.1.0.dist-info/entry_points.txt
atom_flight_manual_zh_cn-2024.3.1.0.dist-info/top_level.txt
atom_flight_manual_zh_cn-2024.3.1.0.dist-info/RECORD
